README
setup.cfg
setup.py
uncleschool/__init__.py
uncleschool/studentclass.py
uncleschool.egg-info/PKG-INFO
uncleschool.egg-info/SOURCES.txt
uncleschool.egg-info/dependency_links.txt
uncleschool.egg-info/top_level.txt