Metadata-Version: 1.1
Name: uncleschool
Version: 0.3
Summary: OOP Learning Example by Uncle Engineer
Home-page: https://github.com/UncleEngineer/uncleschool
Author: Uncle Engineer
Author-email: loong.wissawakorn@gmail.com
License: MIT
Download-URL: https://github.com/UncleEngineer/uncleschool/archive/v_01.tar.gz
Keywords: OOP Python,THAI,Uncle Engineer
Platform: UNKNOWN
Classifier: Development Status :: 3 - Alpha
Classifier: Intended Audience :: Developers
Classifier: Topic :: Software Development :: Build Tools
Classifier: License :: OSI Approved :: MIT License
Classifier: Programming Language :: Python :: 3
Classifier: Programming Language :: Python :: 3.4
Classifier: Programming Language :: Python :: 3.5
Classifier: Programming Language :: Python :: 3.6
Classifier: Programming Language :: Python :: 3.7
Classifier: Programming Language :: Python :: 3.8
Classifier: Programming Language :: Python :: 3.9
